unidns/__init__.py
unidns/_version.py
unidns/client.py
unidns/common/__init__.py
unidns/common/factory.py
unidns/common/settings.py
unidns/examples/__init__.py
unidns/examples/unidnsclient.py
unidns/network/__init__.py
unidns/network/packetizer.py
unidns/protocol/__init__.py
unidns/protocol/structs.py
unidns-0.0.3.dist-info/LICENSE
unidns-0.0.3.dist-info/METADATA
unidns-0.0.3.dist-info/WHEEL
unidns-0.0.3.dist-info/entry_points.txt
unidns-0.0.3.dist-info/top_level.txt
unidns-0.0.3.dist-info/zip-safe
unidns-0.0.3.dist-info/RECORD
