Metadata-Version: 2.1
Name: unidns
Version: 0.0.3
Summary: Rudimentary async DNS client in Python
Home-page: https://github.com/skelsec/unidns
Author: Tamas Jos
Author-email: info@skelsecprojects.com
Classifier: Programming Language :: Python :: 3.6
Classifier: License :: OSI Approved :: MIT License
Classifier: Operating System :: OS Independent
Requires-Python: >=3.6
License-File: LICENSE
Requires-Dist: asysocks (>=0.2.7)
